apphub_configurator/__about__.py
apphub_configurator/__init__.py
apphub_configurator/helpers.py
apphub_configurator/models.py
apphub_configurator-0.0.6.dist-info/METADATA
apphub_configurator-0.0.6.dist-info/WHEEL
apphub_configurator-0.0.6.dist-info/licenses/LICENSE.txt
apphub_configurator-0.0.6.dist-info/RECORD
